[
  {
    "latin": "aai",
    "thaana": "އާއި"
  },
  {
    "latin": "adhi",
    "thaana": "އަދި"
  },
  {
    "latin": "ah",
    "thaana": "އަށް"
  },
  {
    "latin": "aharah",
    "thaana": "އަހަރަށް"
  },
  {
    "latin": "akah",
    "thaana": "އަކަށް"
  },
  {
    "latin": "beynunkurun",
    "thaana": "ބޭނުންކުރުން"
  },
  {
    "latin": "boegen",
    "thaana": "ބޯއެން"
  },
  {
    "latin": "career",
    "thaana": "ކަރީރާ"
  },
  {
    "latin": "chandler",
    "thaana": "ޗެނޑދެ"
  },
  {
    "latin": "clooney",
    "thaana": "ކްލޫނީ"
  },
  {
    "latin": "deepika",
    "thaana": "ޑީޕިކާ"
  },
  {
    "latin": "dhamahattan",
    "thaana": "ދަމަހައްޓަން"
  },
  {
    "latin": "dhigu",
    "thaana": "ދިގު"
  },
  {
    "latin": "dhuvasvee",
    "thaana": "ދުވަސްވީ"
  },
  {
    "latin": "eh",
    "thaana": "އެއް"
  },
  {
    "latin": "eri",
    "thaana": "އެރި"
  },
  {
    "latin": "fahu",
    "thaana": "ފަހު"
  },
  {
    "latin": "faisaa",
    "thaana": "ފައިސާ"
  },
  {
    "latin": "faraathah",
    "thaana": "ފަރާތަށް"
  },
  {
    "latin": "faraathugai",
    "thaana": "ފަރާތުގައި"
  },
  {
    "latin": "fen",
    "thaana": "ފެން"
  },
  {
    "latin": "feshunee",
    "thaana": "ފެށުނީ"
  },
  {
    "latin": "film",
    "thaana": "ފިލްމު"
  },
  {
    "latin": "firihenunnakah",
    "thaana": "ފިރިހެނުންނަކަށް"
  },
  {
    "latin": "fonuvaali",
    "thaana": "ފޮނުވާލި"
  },
  {
    "latin": "gai",
    "thaana": "ގައި"
  },
  {
    "latin": "gai",
    "thaana": "ގައި"
  },
  {
    "latin": "gamuga",
    "thaana": "ގަމުގ"
  },
  {
    "latin": "george",
    "thaana": "ގިއާެ"
  },
  {
    "latin": "gina",
    "thaana": "ގިނަ"
  },
  {
    "latin": "hikeytha",
    "thaana": "ހިކޭތަ"
  },
  {
    "latin": "himaayaiy",
    "thaana": "ހިމާޔަތް"
  },
  {
    "latin": "hoonu",
    "thaana": "ހޫނު"
  },
  {
    "latin": "huddha",
    "thaana": "ހުއްދަ"
  },
  {
    "latin": "hushahelhi",
    "thaana": "ހުށަހެޅި"
  },
  {
    "latin": "irumathee",
    "thaana": "އިރަމަތީ"
  },
  {
    "latin": "ithuru",
    "thaana": "އިތުރު"
  },
  {
    "latin": "kaiveni",
    "thaana": "ކައިވެނި"
  },
  {
    "latin": "king",
    "thaana": "ކިންގް"
  },
  {
    "latin": "kulhen",
    "thaana": "ކުޅެން"
  },
  {
    "latin": "kurimatheegai",
    "thaana": "ކުރިމަތީގައި"
  },
  {
    "latin": "kurumah",
    "thaana": "ކުރުމަށް"
  },
  {
    "latin": "kyle",
    "thaana": "ކަލްލީ"
  },
  {
    "latin": "laamu",
    "thaana": "ލާމު"
  },
  {
    "latin": "lanee",
    "thaana": "ލަނީ"
  },
  {
    "latin": "league",
    "thaana": "ލީގު"
  },
  {
    "latin": "loaiybakun",
    "thaana": "ލޯތްބަކުން"
  },
  {
    "latin": "male'",
    "thaana": "މާލެ"
  },
  {
    "latin": "manaakoffi",
    "thaana": "މަނާކޮށްފި"
  },
  {
    "latin": "maruvejje",
    "thaana": "މަރުވެއްޖެ"
  },
  {
    "latin": "meehaku",
    "thaana": "މީހަކު"
  },
  {
    "latin": "mi",
    "thaana": "މި"
  },
  {
    "latin": "miskiy",
    "thaana": "މިސްކިތ"
  },
  {
    "latin": "missile",
    "thaana": "މިސިއިލް"
  },
  {
    "latin": "miuzikee",
    "thaana": "މިއުޒީކްކާ"
  },
  {
    "latin": "moodhah",
    "thaana": "މޫދަށް"
  },
  {
    "latin": "nudhin",
    "thaana": "ނުދިން"
  },
  {
    "latin": "nufennaane",
    "thaana": "ނުފެންނާނެ"
  },
  {
    "latin": "nufudhey",
    "thaana": "ނުފުދޭ"
  },
  {
    "latin": "oiy",
    "thaana": "އޮތް"
  },
  {
    "latin": "othas",
    "thaana": "އޮތަސަ"
  },
  {
    "latin": "party",
    "thaana": "ޕާޓީ"
  },
  {
    "latin": "premier",
    "thaana": "ޕްރިމިއާ"
  },
  {
    "latin": "raihan",
    "thaana": "ރައިހަން"
  },
  {
    "latin": "ranveer",
    "thaana": "ރަންވީރު"
  },
  {
    "latin": "role",
    "thaana": "ރޯލް"
  },
  {
    "latin": "russia",
    "thaana": "ރަޝިޔާ"
  },
  {
    "latin": "salman",
    "thaana": "ސަލްމާން"
  },
  {
    "latin": "soikoffi",
    "thaana": "ސޮއިކޮށްފި"
  },
  {
    "latin": "syria",
    "thaana": "ސީރިއާ"
  },
  {
    "latin": "telegram",
    "thaana": "ޓެލަގްރާމް"
  },
  {
    "latin": "thee",
    "thaana": "ތީ"
  },
  {
    "latin": "thotteh",
    "thaana": "ތޮޓްޓެއް"
  },
  {
    "latin": "ufaddhan",
    "thaana": "އުފައްދަން"
  },
  {
    "latin": "ulhunu",
    "thaana": "އުޅުނު"
  },
  {
    "latin": "umurun",
    "thaana": "އުމުރުން"
  },
  {
    "latin": "ves",
    "thaana": "ވެސް"
  },
  {
    "latin": "vure",
    "thaana": "ވުރެ"
  },
  {
    "latin": "wolves",
    "thaana": "ވޮލްވްް"
  },
  {
    "latin": "yaarakee",
    "thaana": "ޔާރަކީ"
  }
]